glabels/__init__.py
glabels/_base.py
glabels/glabels_3.py
glabels/glabels_qt.py
glabels-0.1.3.dist-info/METADATA
glabels-0.1.3.dist-info/WHEEL
glabels-0.1.3.dist-info/top_level.txt
glabels-0.1.3.dist-info/RECORD
