Metadata-Version: 2.1
Name: glabels
Version: 0.1.3
Summary: Simple wrapper around glabels-3-batch and glabels-batch-qt
Author: Nureev Insaf
Author-email: uneenymain@gmail.com
Classifier: Programming Language :: Python :: 3
Requires-Python: >=3.7
